README.rst
setup.py
fortls/__init__.py
fortls/intrinsic_funs.json
fortls/intrinsic_mods.json
fortls/intrinsics.py
fortls/jsonrpc.py
fortls/keywords.json
fortls/langserver.py
fortls/objects.py
fortls/parse_fortran.py
fortls/statements.json
fortran_language_server.egg-info/PKG-INFO
fortran_language_server.egg-info/SOURCES.txt
fortran_language_server.egg-info/dependency_links.txt
fortran_language_server.egg-info/entry_points.txt
fortran_language_server.egg-info/requires.txt
fortran_language_server.egg-info/top_level.txt
test/test_server.py