Metadata-Version: 1.1
Name: fortran-language-server
Version: 1.8.1
Summary: FORTRAN Language Server for the Language Server Protocol
Home-page: https://github.com/hansec/fortran-language-server
Author: Chris Hansen
Author-email: hansec@uw.edu
License: UNKNOWN
Download-URL: https://github.com/hansec/fortran-language-server/archive/v1.8.1.tar.gz
Platform: UNKNOWN
